LICENSE
MANIFEST.in
README.md
setup.cfg
setup.py
pyxero_ni_temp.egg-info/PKG-INFO
pyxero_ni_temp.egg-info/SOURCES.txt
pyxero_ni_temp.egg-info/dependency_links.txt
pyxero_ni_temp.egg-info/pbr.json
pyxero_ni_temp.egg-info/requires.txt
pyxero_ni_temp.egg-info/top_level.txt
tests/__init__.py
tests/auth.py
tests/exceptions.py
tests/manager.py
tests/mock_data.py
xero/__init__.py
xero/api.py
xero/auth.py
xero/constants.py
xero/exceptions.py
xero/filesmanager.py
xero/manager.py
xero/utils.py