Metadata-Version: 1.1
Name: pyxero-ni-temp
Version: 0.7.0-alpha2
Summary: Python API for accessing the REST API of the Xero accounting tool.
Home-page: https://github.com/alexrybrown/pyxero
Author: Alexander Brown
Author-email: alexrybrown@gmail.com
License: New BSD
Platform: UNKNOWN
Classifier: Development Status :: 4 - Beta
Classifier: Environment :: Web Environment
Classifier: Intended Audience :: Financial and Insurance Industry
Classifier: License :: OSI Approved :: BSD License
Classifier: Operating System :: OS Independent
Classifier: Programming Language :: Python
Classifier: Programming Language :: Python :: 2.6
Classifier: Programming Language :: Python :: 2.7
Classifier: Programming Language :: Python :: 3.3
Classifier: Programming Language :: Python :: 3.4
Classifier: Topic :: Office/Business :: Financial :: Accounting
